Workbook
Name aporte: Tabela!$D$16
Name patrimonio_acumulado: Tabela!$D$19
Name rendimento_carteira: Tabela!$D$11
Name rendimento_medio: Tabela!$D$18
Name salario: Tabela!$D$10

Sheet Tabela
B9: CONFIGURAÇÕES
B10: Salário | D10: 4800
B11: Rendimento da carteira | D11: 0.0106
B12: Sugestão de investimento (30%) | D12: =30%*D10 -> 1440
B15: INVESTIMENTO MENSAL
B16: Quanto você vai investir por mês: | D16: 500
B17: Por quantos anos: | D17: 5
B18: Rendimento médio mensal | D18: 0.01
B19: Patrimônio acumulado | D19: =FV(D18,D17*12,D16*-1) -> 40834.835
B20: Dividendos mensais | D20: =D19*D18 -> 408.34835
B23: CENÁRIOS | C23: Patrimônio acumulado | D23: Dividendos
A24: 2 | B24: Quanto em 2 anos | C24: =FV(rendimento_carteira,$A24*12,$D$16*-1) -> 13583.114 | D24: =C24*rendimento_carteira -> 143.98101
A25: 5 | B25: Quanto em 5 anos | C25: =FV(rendimento_carteira,$A25*12,$D$16*-1) -> 41631.99 | D25: =C25*rendimento_carteira -> 441.29909
A26: 10 | B26: Quanto em 10 anos | C26: =FV(rendimento_carteira,$A26*12,$D$16*-1) -> 120008.3 | D26: =C26*rendimento_carteira -> 1272.088
A27: 20 | B27: Quanto em 20 anos | C27: =FV(rendimento_carteira,$A27*12,$D$16*-1) -> 545338.81 | D27: =C27*rendimento_carteira -> 5780.5914
A28: 30 | B28: Quanto em 30 anos | C28: =FV(rendimento_carteira,$A28*12,$D$16*-1) -> 2052785 | D28: =C28*rendimento_carteira -> 21759.521
B31: PERFIL | D31: Conservador
B32: VALOR A SER INVESTIDO | D32: =aporte -> 500
B34: TIPO DE FII | C34: PERCENTUAL SUGERIDO | D34: VALORES (R$)
B35: PAPEL | C35: =VLOOKUP(B35&"-"&$D$31,Auxiliar!$B$3:$E$21,4,FALSE) -> 0.25 | D35: =C35*$D$32 -> 125
B36: TIJOLO | C36: =VLOOKUP(B36&"-"&$D$31,Auxiliar!$B$3:$E$21,4,FALSE) -> 0.3 | D36: =C36*$D$32 -> 150
B37: HÍBRIDOS | C37: =VLOOKUP(B37&"-"&$D$31,Auxiliar!$B$3:$E$21,4,FALSE) -> 0.25 | D37: =C37*$D$32 -> 125
B38: FOFs | C38: =VLOOKUP(B38&"-"&$D$31,Auxiliar!$B$3:$E$21,4,FALSE) -> 0.1 | D38: =C38*$D$32 -> 50
B39: DESENVOLVIMENTO | C39: =VLOOKUP(B39&"-"&$D$31,Auxiliar!$B$3:$E$21,4,FALSE) -> 0.05 | D39: =C39*$D$32 -> 25
B40: HOTELARIAS | C40: =VLOOKUP(B40&"-"&$D$31,Auxiliar!$B$3:$E$21,4,FALSE) -> 0.05 | D40: =C40*$D$32 -> 25
B41: TOTAL | D41: =SUM(D35:D40) -> 500

Sheet Auxiliar
B3: Chave | C3: Perfil | D3: TIPO DE FII | E3: Percentual
B4: =Auxiliar!D4&"-"&Auxiliar!C4 -> PAPEL-Conservador | C4: Conservador | D4: PAPEL | E4: 0.25 | F4: =SUM(E4:E9) -> 1
B5: =Auxiliar!D5&"-"&Auxiliar!C5 -> TIJOLO-Conservador | C5: Conservador | D5: TIJOLO | E5: 0.3
B6: =Auxiliar!D6&"-"&Auxiliar!C6 -> HÍBRIDOS-Conservador | C6: Conservador | D6: HÍBRIDOS | E6: 0.25
B7: =Auxiliar!D7&"-"&Auxiliar!C7 -> FOFs-Conservador | C7: Conservador | D7: FOFs | E7: 0.1
B8: =Auxiliar!D8&"-"&Auxiliar!C8 -> DESENVOLVIMENTO-Conservador | C8: Conservador | D8: DESENVOLVIMENTO | E8: 0.05
B9: =Auxiliar!D9&"-"&Auxiliar!C9 -> HOTELARIAS-Conservador | C9: Conservador | D9: HOTELARIAS | E9: 0.05
B10: =Auxiliar!D10&"-"&Auxiliar!C10 -> PAPEL-Moderado | C10: Moderado | D10: PAPEL | E10: 0.2 | F10: =SUM(E10:E15) -> 1
B11: =Auxiliar!D11&"-"&Auxiliar!C11 -> TIJOLO-Moderado | C11: Moderado | D11: TIJOLO | E11: 0.25
B12: =Auxiliar!D12&"-"&Auxiliar!C12 -> HÍBRIDOS-Moderado | C12: Moderado | D12: HÍBRIDOS | E12: 0.2
B13: =Auxiliar!D13&"-"&Auxiliar!C13 -> FOFs-Moderado | C13: Moderado | D13: FOFs | E13: 0.15
B14: =Auxiliar!D14&"-"&Auxiliar!C14 -> DESENVOLVIMENTO-Moderado | C14: Moderado | D14: DESENVOLVIMENTO | E14: 0.1
B15: =Auxiliar!D15&"-"&Auxiliar!C15 -> HOTELARIAS-Moderado | C15: Moderado | D15: HOTELARIAS | E15: 0.1
B16: =Auxiliar!D16&"-"&Auxiliar!C16 -> PAPEL-Agressivo | C16: Agressivo | D16: PAPEL | E16: 0.2 | F16: =SUM(E16:E21) -> 1
B17: =Auxiliar!D17&"-"&Auxiliar!C17 -> TIJOLO-Agressivo | C17: Agressivo | D17: TIJOLO | E17: 0.2
B18: =Auxiliar!D18&"-"&Auxiliar!C18 -> HÍBRIDOS-Agressivo | C18: Agressivo | D18: HÍBRIDOS | E18: 0.2
B19: =Auxiliar!D19&"-"&Auxiliar!C19 -> FOFs-Agressivo | C19: Agressivo | D19: FOFs | E19: 0.1
B20: =Auxiliar!D20&"-"&Auxiliar!C20 -> DESENVOLVIMENTO-Agressivo | C20: Agressivo | D20: DESENVOLVIMENTO | E20: 0.2
B21: =Auxiliar!D21&"-"&Auxiliar!C21 -> HOTELARIAS-Agressivo | C21: Agressivo | D21: HOTELARIAS | E21: 0.1
